Metadata-Version: 1.0
Name: dap.plugins.netcdf
Version: 0.3.5
Summary: netCDF plugin for pydap server
Home-page: http://pydap.org/plugins/netcdf.html
Author: Roberto De Almeida
Author-email: rob@pydap.org
License: MIT
Keywords: netcdf dap opendap dods data
Platform: UNKNOWN
Classifier: Development Status :: 4 - Beta
Classifier: Environment :: Console
Classifier: Intended Audience :: Developers
Classifier: Intended Audience :: Science/Research
Classifier: License :: OSI Approved :: MIT License
Classifier: Operating System :: OS Independent
Classifier: Programming Language :: Python
Classifier: Topic :: Internet
Classifier: Topic :: Scientific/Engineering
Classifier: Topic :: Software Development :: Libraries :: Python Modules
